krcg_api/__init__.py
krcg_api/api.py
krcg_api/config.py
krcg_api/wsgi.py
krcg_api/templates/index.html
krcg_api/templates/openapi.yaml
krcg_api-3.3.dist-info/licenses/LICENSE
krcg_api-3.3.dist-info/METADATA
krcg_api-3.3.dist-info/WHEEL
krcg_api-3.3.dist-info/entry_points.txt
krcg_api-3.3.dist-info/top_level.txt
krcg_api-3.3.dist-info/RECORD
