Metadata-Version: 2.4
Name: krcg-api
Version: 3.3
Summary: Web API for VTES cards and TWDA
Author-email: Lionel Panhaleux <lionel.panhaleux+krcg@gmail.com>
Project-URL: Homepage, https://api.krcg.org
Project-URL: Repository, https://github.com/lionel-panhaleux/krcg-api
Keywords: vtes,Vampire: The Eternal Struggle,CCG,TWD,TWDA,api,web
Classifier: Programming Language :: Python :: 3
Classifier: Programming Language :: Python :: 3.10
Classifier: Programming Language :: Python :: 3.11
Classifier: License :: OSI Approved :: MIT License
Classifier: Development Status :: 5 - Production/Stable
Classifier: Intended Audience :: Developers
Classifier: Natural Language :: English
Classifier: Operating System :: OS Independent
Classifier: Environment :: Web Environment
Classifier: Framework :: Flask
Classifier: Topic :: Games/Entertainment
Classifier: Topic :: Internet :: WWW/HTTP :: WSGI :: Server
Requires-Python: >=3.10
License-File: LICENSE
Requires-Dist: arrow
Requires-Dist: babel
Requires-Dist: flask
Requires-Dist: krcg>=4.14
Requires-Dist: requests
Provides-Extra: dev
Requires-Dist: black; extra == "dev"
Requires-Dist: ipython; extra == "dev"
Requires-Dist: openapi-spec-validator; extra == "dev"
Requires-Dist: pytest; extra == "dev"
Requires-Dist: ruff; extra == "dev"
Requires-Dist: zest.releaser[recommended]; extra == "dev"
Dynamic: license-file
